commandflow/__init__.py
commandflow/action.py
commandflow/command.py
commandflow/preset/__init__.py
commandflow/preset/base.py
commandflow/preset/fastp/fastp.py
commandflow/preset/fastp/README.md
commandflow/preset/wget/wget.py
commandflow-0.1.3.dist-info/WHEEL
commandflow-0.1.3.dist-info/METADATA
commandflow-0.1.3.dist-info/RECORD
