Metadata-Version: 2.1
Name: commandflow
Version: 0.1.3
Summary: Writing shell by python.
Home-page: https://github.com/dwpeng/commandflow
Author: dwpeng
Author-email: 1732889554@qq.com
Requires-Python: >=3.7,<4.0
Classifier: Programming Language :: Python :: 3
Classifier: Programming Language :: Python :: 3.7
Classifier: Programming Language :: Python :: 3.8
Classifier: Programming Language :: Python :: 3.9
Classifier: Programming Language :: Python :: 3.10
Classifier: Programming Language :: Python :: 3.11
Project-URL: Repository, https://github.com/dwpeng/commandflow
